styler_rest_framework/__init__.py
styler_rest_framework/alerts/__init__.py
styler_rest_framework/alerts/slack.py
styler_rest_framework/api/__init__.py
styler_rest_framework/api/authorization.py
styler_rest_framework/api/request_scope.py
styler_rest_framework/api/responses.py
styler_rest_framework/business/__init__.py
styler_rest_framework/config/__init__.py
styler_rest_framework/config/defaults.py
styler_rest_framework/controllers/__init__.py
styler_rest_framework/controllers/request_scope.py
styler_rest_framework/crypto/__init__.py
styler_rest_framework/crypto/aes.py
styler_rest_framework/datasource/__init__.py
styler_rest_framework/datasource/firestore.py
styler_rest_framework/datasource/session_scope.py
styler_rest_framework/datasource/sqlalchemy/__init__.py
styler_rest_framework/datasource/sqlalchemy/session.py
styler_rest_framework/events/__init__.py
styler_rest_framework/events/user_event.py
styler_rest_framework/exceptions/__init__.py
styler_rest_framework/exceptions/business/__init__.py
styler_rest_framework/exceptions/services/__init__.py
styler_rest_framework/helpers/__init__.py
styler_rest_framework/helpers/aiohttp_defaults.py
styler_rest_framework/helpers/fastapi_defaults.py
styler_rest_framework/helpers/gcs_handler.py
styler_rest_framework/helpers/jwt_validator.py
styler_rest_framework/helpers/logme.py
styler_rest_framework/helpers/mailer.py
styler_rest_framework/helpers/migration.py
styler_rest_framework/helpers/paginator.py
styler_rest_framework/logging/__init__.py
styler_rest_framework/logging/error_reporting.py
styler_rest_framework/logging/logging_filter.py
styler_rest_framework/message/__init__.py
styler_rest_framework/message/labels/pydantic_validation.en.yml
styler_rest_framework/message/labels/pydantic_validation.ja.yml
styler_rest_framework/message/labels/validation.en.yml
styler_rest_framework/message/labels/validation.ja.yml
styler_rest_framework/middlewares/__init__.py
styler_rest_framework/middlewares/aiohttp/__init__.py
styler_rest_framework-1.18.2.dist-info/LICENSE
styler_rest_framework-1.18.2.dist-info/METADATA
styler_rest_framework-1.18.2.dist-info/WHEEL
styler_rest_framework-1.18.2.dist-info/top_level.txt
styler_rest_framework-1.18.2.dist-info/RECORD
